[
    {
        "compliance_statement": 0,
        "compliance_data": 0,
        "date": 0,
        "business_entity": 0,
        "regulation": 0,
        "text": "ADVANCED"
    },
    {
        "compliance_statement": 0,
        "compliance_data": 0,
        "date": 0,
        "business_entity": 0,
        "regulation": 0,
        "text": "INTERCONNECTIONS"
    },
    {
        "compliance_statement": 0,
        "compliance_data": 0,
        "date": 0,
        "business_entity": 0,
        "regulation": 0,
        "text": "February 2024"
    },
    {
        "compliance_statement": 1,
        "compliance_data": 1,
        "date": 0,
        "business_entity": 0,
        "regulation": 1,
        "text": "REACH Compliance Statement"
    },
    {
        "compliance_statement": 0,
        "compliance_data": 0,
        "date": 0,
        "business_entity": 0,
        "regulation": 0,
        "text": "(Registration, Evaluation, Authorization and Restriction of Chemicals)."
    },
    {
        "compliance_statement": 1,
        "compliance_data": 1,
        "date": 0,
        "business_entity": 0,
        "regulation": 1,
        "text": "Reference: ECHA, Candidate list of Substances of Very High Concern (SVHC) https://echa.europa.eu/candidate-list-table",
        "business_entity_confidence": 0.9965301156044006
    },
    {
        "compliance_statement": 1,
        "compliance_data": 1,
        "date": 0,
        "business_entity": 0,
        "regulation": 1,
        "text": "ECHA, Substances restricted under REACH Annex XVII https://echa.europa.eu/substances-restricted-under-reach.",
        "business_entity_confidence": 0.998496413230896
    },
    {
        "compliance_statement": 0,
        "compliance_data": 1,
        "date": 0,
        "business_entity": 1,
        "regulation": 1,
        "text": "Advanced Interconnections Corp. (AIC) is a producer of articles for sale under the European Union's REACH",
        "business_entity_confidence": 0.9995914101600647
    },
    {
        "compliance_statement": 0,
        "compliance_data": 1,
        "date": 0,
        "business_entity": 0,
        "regulation": 0,
        "text": "Regulation (EC) No. 1907/2006. These articles may be exported directly to the European Union or they may",
        "business_entity_confidence": 0.999371349811554
    },
    {
        "compliance_statement": 1,
        "compliance_data": 1,
        "date": 0,
        "business_entity": 0,
        "regulation": 0,
        "text": "eventually be included in other products exported to the European Union. All active products manufactured by.",
        "business_entity_confidence": 0.9992965459823608
    },
    {
        "compliance_statement": 1,
        "compliance_data": 1,
        "date": 0,
        "business_entity": 1,
        "regulation": 1,
        "text": "Advanced Interconnections Corp. (articles and all packaging materials for these articles) comply with REACH",
        "business_entity_confidence": 0.99954754114151
    },
    {
        "compliance_statement": 1,
        "compliance_data": 1,
        "date": 0,
        "business_entity": 0,
        "regulation": 1,
        "text": "regulations and meet the restrictions described under REACH Annex XVHI."
    },
    {
        "compliance_statement": 0,
        "compliance_data": 0,
        "date": 0,
        "business_entity": 0,
        "regulation": 0,
        "text": "The Regulation exempts producers from certain substance reporting obligations, where they can exclude."
    },
    {
        "compliance_statement": 0,
        "compliance_data": 0,
        "date": 0,
        "business_entity": 0,
        "regulation": 0,
        "text": "exposure of the substance to humans or the environment during normal or reasonably foreseeable conditions of"
    },
    {
        "compliance_statement": 0,
        "compliance_data": 1,
        "date": 0,
        "business_entity": 0,
        "regulation": 1,
        "text": "use. In addition, the recent European Chemicals Agency (ECHA) Response to Comments on the SVHC",
        "business_entity_confidence": 0.9977224469184875
    },
    {
        "compliance_statement": 0,
        "compliance_data": 0,
        "date": 0,
        "business_entity": 0,
        "regulation": 0,
        "text": "Proposal for the Eventual Inclusion of Lead in Annex XIV explicitly states that the inclusion of lead (Pb) on the"
    },
    {
        "compliance_statement": 0,
        "compliance_data": 1,
        "date": 0,
        "business_entity": 0,
        "regulation": 1,
        "text": "SVHC list does not intend a general ban on lead in products at this time..",
        "business_entity_confidence": 0.9986831545829773
    },
    {
        "compliance_statement": 0,
        "compliance_data": 1,
        "date": 0,
        "business_entity": 0,
        "regulation": 0,
        "text": "Many of the products manufactured and sold by AIC contain components made of a copper alloy (brass)",
        "business_entity_confidence": 0.9995254278182983
    },
    {
        "compliance_statement": 1,
        "compliance_data": 1,
        "date": 0,
        "business_entity": 0,
        "regulation": 1,
        "text": "Copper alloy contains lead. RoHS exemption 6C currently allows for lead (Pb), CAS 7439-92-1 of up to 4% by",
        "business_entity_confidence": 0.9823540449142456
    },
    {
        "compliance_statement": 0,
        "compliance_data": 1,
        "date": 0,
        "business_entity": 0,
        "regulation": 0,
        "text": "weight. AIC testing is not performed for materials and substances that were not intentionally added. No.",
        "business_entity_confidence": 0.9990181922912598
    },
    {
        "compliance_statement": 0,
        "compliance_data": 0,
        "date": 0,
        "business_entity": 0,
        "regulation": 0,
        "text": "warranty, liability of indemnification is expressed or implied with this information.."
    },
    {
        "compliance_statement": 0,
        "compliance_data": 1,
        "date": 1,
        "business_entity": 0,
        "regulation": 0,
        "text": "February 1, 2024"
    },
    {
        "compliance_statement": 0,
        "compliance_data": 0,
        "date": 0,
        "business_entity": 0,
        "regulation": 0,
        "text": "Glenn Goodman"
    },
    {
        "compliance_statement": 0,
        "compliance_data": 0,
        "date": 0,
        "business_entity": 0,
        "regulation": 0,
        "text": "Date"
    },
    {
        "compliance_statement": 0,
        "compliance_data": 0,
        "date": 0,
        "business_entity": 0,
        "regulation": 0,
        "text": "Engineering Manager"
    },
    {
        "compliance_statement": 0,
        "compliance_data": 1,
        "date": 0,
        "business_entity": 1,
        "regulation": 0,
        "text": "Advanced Interconnections Corp.-5 Energy Way-WestWarwick,Rhode Island 02893-2389-USA",
        "business_entity_confidence": 0.9995834231376648
    },
    {
        "compliance_statement": 0,
        "compliance_data": 0,
        "date": 0,
        "business_entity": 0,
        "regulation": 0,
        "text": "401-823-5200-800-424-9850-Fax401-823-8723-info@advanced.com=www.advanced.com"
    },
    {
        "compliance_statement": 0,
        "compliance_data": 1,
        "date": 0,
        "business_entity": 0,
        "regulation": 0,
        "text": "ECN# 23457",
        "business_entity_confidence": 0.9920743703842163
    }
]