[
    {
        "compliance_statement": 1,
        "compliance_data": 1,
        "date": 0,
        "business_entity": 0,
        "regulation": 1,
        "text": "Toxic Substances Control Act (TsCA) Statement."
    },
    {
        "compliance_statement": 0,
        "compliance_data": 1,
        "date": 0,
        "business_entity": 0,
        "regulation": 1,
        "text": "If you have questions regarding the applicability of TsCA"
    },
    {
        "compliance_statement": 0,
        "compliance_data": 1,
        "date": 0,
        "business_entity": 0,
        "regulation": 1,
        "text": "to your product(s), contact the TSCA Hotline at (202) 554-1404",
        "business_entity_confidence": 0.9957687854766846
    },
    {
        "compliance_statement": 0,
        "compliance_data": 0,
        "date": 0,
        "business_entity": 0,
        "regulation": 0,
        "text": "Please check the appropriate box below:."
    },
    {
        "compliance_statement": 0,
        "compliance_data": 0,
        "date": 0,
        "business_entity": 0,
        "regulation": 0,
        "text": "Positive Statement:."
    },
    {
        "compliance_statement": 1,
        "compliance_data": 0,
        "date": 0,
        "business_entity": 0,
        "regulation": 0,
        "text": "I certify that all chemical substances in this shipment comply with all"
    },
    {
        "compliance_statement": 1,
        "compliance_data": 1,
        "date": 0,
        "business_entity": 0,
        "regulation": 1,
        "text": "applicable rules or orders under TsCA, and that I am not offering a",
        "business_entity_confidence": 0.9951861500740051
    },
    {
        "compliance_statement": 1,
        "compliance_data": 1,
        "date": 0,
        "business_entity": 0,
        "regulation": 1,
        "text": "chemical substance for entry in violation of TsCA or any applicable"
    },
    {
        "compliance_statement": 1,
        "compliance_data": 0,
        "date": 0,
        "business_entity": 0,
        "regulation": 0,
        "text": "rule or order thereunder.."
    },
    {
        "compliance_statement": 0,
        "compliance_data": 0,
        "date": 0,
        "business_entity": 0,
        "regulation": 0,
        "text": "Negative Statement:"
    },
    {
        "compliance_statement": 1,
        "compliance_data": 1,
        "date": 0,
        "business_entity": 0,
        "regulation": 1,
        "text": "I certify that all chemicals in this shipment are not subject to TsCA"
    },
    {
        "compliance_statement": 0,
        "compliance_data": 0,
        "date": 0,
        "business_entity": 0,
        "regulation": 0,
        "text": "Company Name:"
    },
    {
        "compliance_statement": 0,
        "compliance_data": 0,
        "date": 0,
        "business_entity": 0,
        "regulation": 0,
        "text": "Authorized Name (Please print):."
    },
    {
        "compliance_statement": 0,
        "compliance_data": 0,
        "date": 0,
        "business_entity": 0,
        "regulation": 0,
        "text": "Title:"
    },
    {
        "compliance_statement": 0,
        "compliance_data": 0,
        "date": 0,
        "business_entity": 0,
        "regulation": 0,
        "text": "Date (mm/dd/yy):"
    },
    {
        "compliance_statement": 0,
        "compliance_data": 0,
        "date": 0,
        "business_entity": 0,
        "regulation": 0,
        "text": "Signature:"
    },
    {
        "compliance_statement": 0,
        "compliance_data": 1,
        "date": 0,
        "business_entity": 0,
        "regulation": 1,
        "text": "TSCA Statement Rev Feb 2013",
        "business_entity_confidence": 0.995376706123352
    }
]